{
 "updated": "2026-07-17 17:47:35 UTC",
 "quotes": {
  "2B70": {
   "c": 8.378000259399414,
   "pc": 8.35,
   "cur": "EUR",
   "sym": "2B70.DE"
  },
  "APP": {
   "c": 428.92498779296875,
   "pc": 435.79,
   "cur": "USD",
   "sym": "APP"
  },
  "AMZN": {
   "c": 247.8699951171875,
   "pc": 250.9251,
   "cur": "USD",
   "sym": "AMZN"
  },
  "ASTS": {
   "c": 59.880001068115234,
   "pc": 54.1768,
   "cur": "USD",
   "sym": "ASTS"
  },
  "ARM": {
   "c": 270.760009765625,
   "pc": 257.4353,
   "cur": "USD",
   "sym": "ARM"
  },
  "AAOI": {
   "c": 104.2699966430664,
   "pc": 98.43,
   "cur": "USD",
   "sym": "AAOI"
  },
  "ASML": {
   "c": 1537.0,
   "pc": 1592.0,
   "cur": "EUR",
   "sym": "ASML.AS"
  },
  "AVGO": {
   "c": 375.21929931640625,
   "pc": 373.9,
   "cur": "USD",
   "sym": "AVGO"
  },
  "BE": {
   "c": 219.38499450683594,
   "pc": 204.8472,
   "cur": "USD",
   "sym": "BE"
  },
  "BWXT": {
   "c": 173.85499572753906,
   "pc": 175.0,
   "cur": "USD",
   "sym": "BWXT"
  },
  "CORZ": {
   "c": 21.290000915527344,
   "pc": 20.611,
   "cur": "USD",
   "sym": "CORZ"
  },
  "CEG": {
   "c": 253.4915008544922,
   "pc": 251.0,
   "cur": "USD",
   "sym": "CEG"
  },
  "CRDO": {
   "c": 206.9600067138672,
   "pc": 204.01,
   "cur": "USD",
   "sym": "CRDO"
  },
  "CRWD": {
   "c": 206.5500946044922,
   "pc": 203.94,
   "cur": "USD",
   "sym": "CRWD"
  },
  "CRWV": {
   "c": 73.94999694824219,
   "pc": 71.64,
   "cur": "USD",
   "sym": "CRWV"
  },
  "DDOG": {
   "c": 259.6000061035156,
   "pc": 263.4541,
   "cur": "USD",
   "sym": "DDOG"
  },
  "FLNC": {
   "c": 14.199999809265137,
   "pc": 14.26,
   "cur": "USD",
   "sym": "FLNC"
  },
  "DELL": {
   "c": 404.135009765625,
   "pc": 384.25,
   "cur": "USD",
   "sym": "DELL"
  },
  "HIMS": {
   "c": 33.310001373291016,
   "pc": 33.395,
   "cur": "USD",
   "sym": "HIMS"
  },
  "ISRG": {
   "c": 349.3800048828125,
   "pc": 358.91,
   "cur": "USD",
   "sym": "ISRG"
  },
  "GOOG": {
   "c": 343.82501220703125,
   "pc": 356.71,
   "cur": "USD",
   "sym": "GOOG"
  },
  "GEV": {
   "c": 1063.320068359375,
   "pc": 1023.06,
   "cur": "USD",
   "sym": "GEV"
  },
  "JEDI": {
   "c": 69.7699966430664,
   "pc": 70.77,
   "cur": "EUR",
   "sym": "JEDI.DE"
  },
  "INTC": {
   "c": 96.4800033569336,
   "pc": 95.1698,
   "cur": "USD",
   "sym": "INTC"
  },
  "LITE": {
   "c": 741.530029296875,
   "pc": 694.99,
   "cur": "USD",
   "sym": "LITE"
  },
  "KTOS": {
   "c": 46.91999816894531,
   "pc": 47.2,
   "cur": "USD",
   "sym": "KTOS"
  },
  "MRVL": {
   "c": 192.02999877929688,
   "pc": 185.75,
   "cur": "USD",
   "sym": "MRVL"
  },
  "META": {
   "c": 648.3350219726562,
   "pc": 666.755,
   "cur": "USD",
   "sym": "META"
  },
  "MU": {
   "c": 888.5250244140625,
   "pc": 832.41,
   "cur": "USD",
   "sym": "MU"
  },
  "LLY": {
   "c": 1175.824951171875,
   "pc": 1172.0,
   "cur": "USD",
   "sym": "LLY"
  },
  "MSFT": {
   "c": 394.989990234375,
   "pc": 400.2114,
   "cur": "USD",
   "sym": "MSFT"
  },
  "MELI": {
   "c": 1825.6500244140625,
   "pc": 1853.79,
   "cur": "USD",
   "sym": "MELI"
  },
  "NBIS": {
   "c": 186.19000244140625,
   "pc": 167.05,
   "cur": "USD",
   "sym": "NBIS"
  },
  "NOA3": {
   "c": 8.826000213623047,
   "pc": 9.188,
   "cur": "EUR",
   "sym": "NOA3.DE"
  },
  "NVDA": {
   "c": 205.19900512695312,
   "pc": 205.965,
   "cur": "USD",
   "sym": "NVDA"
  },
  "ONDS": {
   "c": 6.66349983215332,
   "pc": 6.56,
   "cur": "USD",
   "sym": "ONDS"
  },
  "NOW": {
   "c": 104.41999816894531,
   "pc": 103.15,
   "cur": "USD",
   "sym": "NOW"
  },
  "PLTR": {
   "c": 134.27000427246094,
   "pc": 132.94,
   "cur": "USD",
   "sym": "PLTR"
  },
  "QUTM": {
   "c": 23.344999313354492,
   "pc": 23.885,
   "cur": "EUR",
   "sym": "QUTM.DE"
  },
  "SGLN": {
   "c": 5783.0,
   "pc": 5776.0,
   "cur": "GBp",
   "sym": "SGLN.L"
  },
  "RCAT": {
   "c": 7.84499979019165,
   "pc": 7.6596,
   "cur": "USD",
   "sym": "RCAT"
  },
  "RBRK": {
   "c": 79.47000122070312,
   "pc": 79.43,
   "cur": "USD",
   "sym": "RBRK"
  },
  "SMTC": {
   "c": 126.00499725341797,
   "pc": 126.3,
   "cur": "USD",
   "sym": "SMTC"
  },
  "SNOW": {
   "c": 269.2049865722656,
   "pc": 267.25,
   "cur": "USD",
   "sym": "SNOW"
  },
  "TEM": {
   "c": 53.19499969482422,
   "pc": 53.0372,
   "cur": "USD",
   "sym": "TEM"
  },
  "WEBN": {
   "c": 12.604000091552734,
   "pc": 12.762,
   "cur": "EUR",
   "sym": "WEBN.DE"
  },
  "UUUU": {
   "c": 11.692000389099121,
   "pc": 11.6781,
   "cur": "USD",
   "sym": "UUUU"
  },
  "ZETA": {
   "c": 22.3700008392334,
   "pc": 21.24,
   "cur": "USD",
   "sym": "ZETA"
  }
 },
 "proxied": [],
 "extra": {
  "TSM": {
   "c": 401.09991455078125,
   "pc": 406.3465,
   "cur": "USD"
  },
  "SNDK": {
   "c": 1457.050048828125,
   "pc": 1366.0,
   "cur": "USD"
  },
  "AVAV": {
   "c": 146.8300018310547,
   "pc": 148.11,
   "cur": "USD"
  },
  "LHX": {
   "c": 283.3900146484375,
   "pc": 283.3,
   "cur": "USD"
  },
  "CCJ": {
   "c": 86.0802993774414,
   "pc": 87.22,
   "cur": "USD"
  },
  "LMT": {
   "c": 511.5350036621094,
   "pc": 512.55,
   "cur": "USD"
  },
  "NOC": {
   "c": 524.4299926757812,
   "pc": 518.65,
   "cur": "USD"
  },
  "RTX": {
   "c": 194.4149932861328,
   "pc": 194.08,
   "cur": "USD"
  },
  "TSLA": {
   "c": 382.3900146484375,
   "pc": 388.6507,
   "cur": "USD"
  },
  "SOFI": {
   "c": 17.5049991607666,
   "pc": 17.31,
   "cur": "USD"
  },
  "SMCI": {
   "c": 25.0049991607666,
   "pc": 24.63,
   "cur": "USD"
  },
  "QQQ": {
   "c": 699.8400268554688,
   "pc": 702.94,
   "cur": "USD"
  },
  "AAPL": {
   "c": 330.8301086425781,
   "pc": 334.8322,
   "cur": "USD"
  },
  "AMD": {
   "c": 502.44970703125,
   "pc": 494.3,
   "cur": "USD"
  },
  "ORCL": {
   "c": 127.9406967163086,
   "pc": 123.58,
   "cur": "USD"
  },
  "SPY": {
   "c": 745.519287109375,
   "pc": 749.1675,
   "cur": "USD"
  },
  "NFLX": {
   "c": 68.69499969482422,
   "pc": 67.6185,
   "cur": "USD"
  },
  "COIN": {
   "c": 160.02999877929688,
   "pc": 159.75,
   "cur": "USD"
  }
 },
 "fx": {
  "GBPEUR": 1.1759999990463257,
  "EURUSD": 1.1437721252441406
 }
}