{
 "updated": "2026-07-17 18:55:04 UTC",
 "quotes": {
  "AAOI": {
   "c": 102.55000305175781,
   "pc": 98.43,
   "cur": "USD",
   "sym": "AAOI"
  },
  "ASTS": {
   "c": 58.73500061035156,
   "pc": 54.1768,
   "cur": "USD",
   "sym": "ASTS"
  },
  "AMZN": {
   "c": 247.7100067138672,
   "pc": 250.9251,
   "cur": "USD",
   "sym": "AMZN"
  },
  "2B70": {
   "c": 8.378000259399414,
   "pc": 8.35,
   "cur": "EUR",
   "sym": "2B70.DE"
  },
  "APP": {
   "c": 424.8500061035156,
   "pc": 435.79,
   "cur": "USD",
   "sym": "APP"
  },
  "ASML": {
   "c": 1537.0,
   "pc": 1592.0,
   "cur": "EUR",
   "sym": "ASML.AS"
  },
  "BE": {
   "c": 215.79989624023438,
   "pc": 204.8472,
   "cur": "USD",
   "sym": "BE"
  },
  "BWXT": {
   "c": 172.77000427246094,
   "pc": 175.0,
   "cur": "USD",
   "sym": "BWXT"
  },
  "CRDO": {
   "c": 206.0050048828125,
   "pc": 204.01,
   "cur": "USD",
   "sym": "CRDO"
  },
  "CORZ": {
   "c": 21.030000686645508,
   "pc": 20.611,
   "cur": "USD",
   "sym": "CORZ"
  },
  "CEG": {
   "c": 252.92999267578125,
   "pc": 251.0,
   "cur": "USD",
   "sym": "CEG"
  },
  "ARM": {
   "c": 267.69000244140625,
   "pc": 257.4353,
   "cur": "USD",
   "sym": "ARM"
  },
  "AVGO": {
   "c": 373.6300048828125,
   "pc": 373.9,
   "cur": "USD",
   "sym": "AVGO"
  },
  "CRWV": {
   "c": 73.84850311279297,
   "pc": 71.64,
   "cur": "USD",
   "sym": "CRWV"
  },
  "DELL": {
   "c": 401.7200012207031,
   "pc": 384.25,
   "cur": "USD",
   "sym": "DELL"
  },
  "DDOG": {
   "c": 258.8699951171875,
   "pc": 263.4541,
   "cur": "USD",
   "sym": "DDOG"
  },
  "FLNC": {
   "c": 13.970000267028809,
   "pc": 14.26,
   "cur": "USD",
   "sym": "FLNC"
  },
  "GEV": {
   "c": 1054.1650390625,
   "pc": 1023.06,
   "cur": "USD",
   "sym": "GEV"
  },
  "HIMS": {
   "c": 33.06999969482422,
   "pc": 33.395,
   "cur": "USD",
   "sym": "HIMS"
  },
  "ISRG": {
   "c": 350.2449951171875,
   "pc": 358.91,
   "cur": "USD",
   "sym": "ISRG"
  },
  "JEDI": {
   "c": 69.7699966430664,
   "pc": 70.77,
   "cur": "EUR",
   "sym": "JEDI.DE"
  },
  "CRWD": {
   "c": 204.33999633789062,
   "pc": 203.94,
   "cur": "USD",
   "sym": "CRWD"
  },
  "LITE": {
   "c": 736.7249755859375,
   "pc": 694.99,
   "cur": "USD",
   "sym": "LITE"
  },
  "KTOS": {
   "c": 46.5,
   "pc": 47.2,
   "cur": "USD",
   "sym": "KTOS"
  },
  "INTC": {
   "c": 95.83989715576172,
   "pc": 95.1698,
   "cur": "USD",
   "sym": "INTC"
  },
  "GOOG": {
   "c": 344.4049987792969,
   "pc": 356.71,
   "cur": "USD",
   "sym": "GOOG"
  },
  "MELI": {
   "c": 1819.969970703125,
   "pc": 1853.79,
   "cur": "USD",
   "sym": "MELI"
  },
  "META": {
   "c": 647.010009765625,
   "pc": 666.755,
   "cur": "USD",
   "sym": "META"
  },
  "MRVL": {
   "c": 189.84500122070312,
   "pc": 185.75,
   "cur": "USD",
   "sym": "MRVL"
  },
  "MSFT": {
   "c": 395.0799865722656,
   "pc": 400.2114,
   "cur": "USD",
   "sym": "MSFT"
  },
  "LLY": {
   "c": 1174.135009765625,
   "pc": 1172.0,
   "cur": "USD",
   "sym": "LLY"
  },
  "MU": {
   "c": 873.8699951171875,
   "pc": 832.41,
   "cur": "USD",
   "sym": "MU"
  },
  "NBIS": {
   "c": 182.7100067138672,
   "pc": 167.05,
   "cur": "USD",
   "sym": "NBIS"
  },
  "NOW": {
   "c": 103.91000366210938,
   "pc": 103.15,
   "cur": "USD",
   "sym": "NOW"
  },
  "NOA3": {
   "c": 8.826000213623047,
   "pc": 9.188,
   "cur": "EUR",
   "sym": "NOA3.DE"
  },
  "ONDS": {
   "c": 6.619999885559082,
   "pc": 6.56,
   "cur": "USD",
   "sym": "ONDS"
  },
  "RCAT": {
   "c": 7.769999980926514,
   "pc": 7.6596,
   "cur": "USD",
   "sym": "RCAT"
  },
  "QUTM": {
   "c": 23.344999313354492,
   "pc": 23.885,
   "cur": "EUR",
   "sym": "QUTM.DE"
  },
  "RBRK": {
   "c": 78.56500244140625,
   "pc": 79.43,
   "cur": "USD",
   "sym": "RBRK"
  },
  "PLTR": {
   "c": 133.1999969482422,
   "pc": 132.94,
   "cur": "USD",
   "sym": "PLTR"
  },
  "NVDA": {
   "c": 203.5500946044922,
   "pc": 205.965,
   "cur": "USD",
   "sym": "NVDA"
  },
  "SGLN": {
   "c": 5783.0,
   "pc": 5776.0,
   "cur": "GBp",
   "sym": "SGLN.L"
  },
  "SMTC": {
   "c": 124.84500122070312,
   "pc": 126.3,
   "cur": "USD",
   "sym": "SMTC"
  },
  "SNOW": {
   "c": 268.42999267578125,
   "pc": 267.25,
   "cur": "USD",
   "sym": "SNOW"
  },
  "TEM": {
   "c": 52.779998779296875,
   "pc": 53.0372,
   "cur": "USD",
   "sym": "TEM"
  },
  "UUUU": {
   "c": 11.625,
   "pc": 11.6781,
   "cur": "USD",
   "sym": "UUUU"
  },
  "ZETA": {
   "c": 22.1200008392334,
   "pc": 21.24,
   "cur": "USD",
   "sym": "ZETA"
  },
  "WEBN": {
   "c": 12.604000091552734,
   "pc": 12.762,
   "cur": "EUR",
   "sym": "WEBN.DE"
  }
 },
 "proxied": [],
 "extra": {
  "SNDK": {
   "c": 1422.3599853515625,
   "pc": 1366.0,
   "cur": "USD"
  },
  "TSM": {
   "c": 397.25,
   "pc": 406.3465,
   "cur": "USD"
  },
  "LHX": {
   "c": 283.5400085449219,
   "pc": 283.3,
   "cur": "USD"
  },
  "NOC": {
   "c": 526.6400146484375,
   "pc": 518.65,
   "cur": "USD"
  },
  "CCJ": {
   "c": 85.5999984741211,
   "pc": 87.22,
   "cur": "USD"
  },
  "RTX": {
   "c": 194.4250030517578,
   "pc": 194.08,
   "cur": "USD"
  },
  "LMT": {
   "c": 510.7749938964844,
   "pc": 512.55,
   "cur": "USD"
  },
  "AVAV": {
   "c": 146.11000061035156,
   "pc": 148.11,
   "cur": "USD"
  },
  "TSLA": {
   "c": 381.9100036621094,
   "pc": 388.6507,
   "cur": "USD"
  },
  "SOFI": {
   "c": 17.354999542236328,
   "pc": 17.31,
   "cur": "USD"
  },
  "SPY": {
   "c": 744.5499877929688,
   "pc": 749.1675,
   "cur": "USD"
  },
  "SMCI": {
   "c": 24.655000686645508,
   "pc": 24.63,
   "cur": "USD"
  },
  "AAPL": {
   "c": 334.239990234375,
   "pc": 334.8322,
   "cur": "USD"
  },
  "AMD": {
   "c": 498.7099914550781,
   "pc": 494.3,
   "cur": "USD"
  },
  "ORCL": {
   "c": 126.43000030517578,
   "pc": 123.58,
   "cur": "USD"
  },
  "QQQ": {
   "c": 698.1699829101562,
   "pc": 702.94,
   "cur": "USD"
  },
  "COIN": {
   "c": 157.97000122070312,
   "pc": 159.75,
   "cur": "USD"
  },
  "NFLX": {
   "c": 69.11499786376953,
   "pc": 67.6185,
   "cur": "USD"
  }
 },
 "fx": {
  "GBPEUR": 1.1759999990463257,
  "EURUSD": 1.1439030170440674
 }
}