{
 "updated": "2026-07-23 18:13:55 UTC",
 "quotes": {
  "APP": {
   "c": 397.7550048828125,
   "pc": 413.3932,
   "cur": "USD",
   "sym": "APP"
  },
  "ARM": {
   "c": 279.510009765625,
   "pc": 282.0,
   "cur": "USD",
   "sym": "ARM"
  },
  "AMZN": {
   "c": 234.1750030517578,
   "pc": 241.962,
   "cur": "USD",
   "sym": "AMZN"
  },
  "2B70": {
   "c": 8.34000015258789,
   "pc": 8.331,
   "cur": "EUR",
   "sym": "2B70.DE"
  },
  "ASTS": {
   "c": 59.314998626708984,
   "pc": 62.2002,
   "cur": "USD",
   "sym": "ASTS"
  },
  "AAOI": {
   "c": 112.5999984741211,
   "pc": 113.3487,
   "cur": "USD",
   "sym": "AAOI"
  },
  "AVGO": {
   "c": 389.95001220703125,
   "pc": 397.6,
   "cur": "USD",
   "sym": "AVGO"
  },
  "ASML": {
   "c": 1579.199951171875,
   "pc": 1585.4000244140625,
   "cur": "EUR",
   "sym": "ASML.AS"
  },
  "BE": {
   "c": 222.19000244140625,
   "pc": 222.95,
   "cur": "USD",
   "sym": "BE"
  },
  "CEG": {
   "c": 274.5199890136719,
   "pc": 273.82,
   "cur": "USD",
   "sym": "CEG"
  },
  "BWXT": {
   "c": 176.86000061035156,
   "pc": 173.7,
   "cur": "USD",
   "sym": "BWXT"
  },
  "CRDO": {
   "c": 234.35000610351562,
   "pc": 231.355,
   "cur": "USD",
   "sym": "CRDO"
  },
  "CRWV": {
   "c": 81.87999725341797,
   "pc": 85.05,
   "cur": "USD",
   "sym": "CRWV"
  },
  "CRWD": {
   "c": 182.8300018310547,
   "pc": 188.99,
   "cur": "USD",
   "sym": "CRWD"
  },
  "CORZ": {
   "c": 24.1200008392334,
   "pc": 24.0,
   "cur": "USD",
   "sym": "CORZ"
  },
  "DDOG": {
   "c": 244.5800018310547,
   "pc": 245.695,
   "cur": "USD",
   "sym": "DDOG"
  },
  "DELL": {
   "c": 439.0741882324219,
   "pc": 441.07,
   "cur": "USD",
   "sym": "DELL"
  },
  "FLNC": {
   "c": 14.46500015258789,
   "pc": 14.71,
   "cur": "USD",
   "sym": "FLNC"
  },
  "GOOG": {
   "c": 320.3550109863281,
   "pc": 331.9079,
   "cur": "USD",
   "sym": "GOOG"
  },
  "ISRG": {
   "c": 331.6000061035156,
   "pc": 341.25,
   "cur": "USD",
   "sym": "ISRG"
  },
  "GEV": {
   "c": 1033.820068359375,
   "pc": 1001.81,
   "cur": "USD",
   "sym": "GEV"
  },
  "INTC": {
   "c": 99.5199966430664,
   "pc": 103.79,
   "cur": "USD",
   "sym": "INTC"
  },
  "HIMS": {
   "c": 33.38999938964844,
   "pc": 31.49,
   "cur": "USD",
   "sym": "HIMS"
  },
  "JEDI": {
   "c": 70.88999938964844,
   "pc": 72.88,
   "cur": "EUR",
   "sym": "JEDI.DE"
  },
  "KTOS": {
   "c": 49.2599983215332,
   "pc": 48.5,
   "cur": "USD",
   "sym": "KTOS"
  },
  "MELI": {
   "c": 1790.8699951171875,
   "pc": 1799.14,
   "cur": "USD",
   "sym": "MELI"
  },
  "META": {
   "c": 606.8499755859375,
   "pc": 619.6544,
   "cur": "USD",
   "sym": "META"
  },
  "LITE": {
   "c": 836.619873046875,
   "pc": 847.45,
   "cur": "USD",
   "sym": "LITE"
  },
  "MRVL": {
   "c": 206.5399932861328,
   "pc": 214.9796,
   "cur": "USD",
   "sym": "MRVL"
  },
  "MSFT": {
   "c": 381.32501220703125,
   "pc": 388.3,
   "cur": "USD",
   "sym": "MSFT"
  },
  "LLY": {
   "c": 1181.280029296875,
   "pc": 1163.26,
   "cur": "USD",
   "sym": "LLY"
  },
  "MU": {
   "c": 991.5,
   "pc": 983.29,
   "cur": "USD",
   "sym": "MU"
  },
  "NBIS": {
   "c": 221.61000061035156,
   "pc": 226.5,
   "cur": "USD",
   "sym": "NBIS"
  },
  "NOW": {
   "c": 93.43000030517578,
   "pc": 99.9,
   "cur": "USD",
   "sym": "NOW"
  },
  "NOA3": {
   "c": 8.739999771118164,
   "pc": 9.196,
   "cur": "EUR",
   "sym": "NOA3.DE"
  },
  "NVDA": {
   "c": 208.77999877929688,
   "pc": 212.04,
   "cur": "USD",
   "sym": "NVDA"
  },
  "ONDS": {
   "c": 7.96999979019165,
   "pc": 8.0098,
   "cur": "USD",
   "sym": "ONDS"
  },
  "PLTR": {
   "c": 122.18000030517578,
   "pc": 125.15,
   "cur": "USD",
   "sym": "PLTR"
  },
  "QUTM": {
   "c": 23.524999618530273,
   "pc": 24.075,
   "cur": "EUR",
   "sym": "QUTM.DE"
  },
  "RBRK": {
   "c": 72.62999725341797,
   "pc": 73.0,
   "cur": "USD",
   "sym": "RBRK"
  },
  "RCAT": {
   "c": 7.934999942779541,
   "pc": 7.9,
   "cur": "USD",
   "sym": "RCAT"
  },
  "SGLN": {
   "c": 5900.0,
   "pc": 6031.0,
   "cur": "GBp",
   "sym": "SGLN.L"
  },
  "SMTC": {
   "c": 135.94000244140625,
   "pc": 137.5,
   "cur": "USD",
   "sym": "SMTC"
  },
  "SNOW": {
   "c": 262.6499938964844,
   "pc": 269.0,
   "cur": "USD",
   "sym": "SNOW"
  },
  "TEM": {
   "c": 45.869998931884766,
   "pc": 47.0663,
   "cur": "USD",
   "sym": "TEM"
  },
  "UUUU": {
   "c": 12.029999732971191,
   "pc": 12.2599,
   "cur": "USD",
   "sym": "UUUU"
  },
  "WEBN": {
   "c": 12.59000015258789,
   "pc": 12.754,
   "cur": "EUR",
   "sym": "WEBN.DE"
  },
  "ZETA": {
   "c": 19.309999465942383,
   "pc": 20.145,
   "cur": "USD",
   "sym": "ZETA"
  }
 },
 "proxied": [],
 "extra": {
  "SNDK": {
   "c": 1667.760009765625,
   "pc": 1620.0,
   "cur": "USD"
  },
  "AVAV": {
   "c": 156.22999572753906,
   "pc": 150.75,
   "cur": "USD"
  },
  "CCJ": {
   "c": 89.41000366210938,
   "pc": 90.43,
   "cur": "USD"
  },
  "NOC": {
   "c": 529.25,
   "pc": 525.0,
   "cur": "USD"
  },
  "RTX": {
   "c": 208.27999877929688,
   "pc": 194.5,
   "cur": "USD"
  },
  "LHX": {
   "c": 296.80499267578125,
   "pc": 284.29,
   "cur": "USD"
  },
  "TSM": {
   "c": 414.885009765625,
   "pc": 422.4,
   "cur": "USD"
  },
  "LMT": {
   "c": 562.5499877929688,
   "pc": 515.2,
   "cur": "USD"
  },
  "TSLA": {
   "c": 320.69000244140625,
   "pc": 358.8,
   "cur": "USD"
  },
  "AAPL": {
   "c": 320.20001220703125,
   "pc": 325.74,
   "cur": "USD"
  },
  "SOFI": {
   "c": 16.665000915527344,
   "pc": 17.0592,
   "cur": "USD"
  },
  "SMCI": {
   "c": 30.815000534057617,
   "pc": 30.9799,
   "cur": "USD"
  },
  "SPY": {
   "c": 737.27001953125,
   "pc": 746.68,
   "cur": "USD"
  },
  "AMD": {
   "c": 536.1300048828125,
   "pc": 554.0,
   "cur": "USD"
  },
  "QQQ": {
   "c": 691.125,
   "pc": 704.78,
   "cur": "USD"
  },
  "ORCL": {
   "c": 119.97000122070312,
   "pc": 126.0,
   "cur": "USD"
  },
  "NFLX": {
   "c": 69.243896484375,
   "pc": 68.5999,
   "cur": "USD"
  },
  "COIN": {
   "c": 162.67010498046875,
   "pc": 167.11,
   "cur": "USD"
  }
 },
 "fx": {
  "GBPEUR": 1.170300006866455,
  "EURUSD": 1.1377859115600586
 }
}